fitinera/__init__.py
fitinera/assets.py
fitinera/cashflows.py
fitinera/core.py
fitinera/planning.py
fitinera/py.typed
fitinera/results.py
fitinera/simulation.py
fitinera-0.1.0.dist-info/WHEEL
fitinera-0.1.0.dist-info/METADATA
fitinera-0.1.0.dist-info/RECORD
