Metadata-Version: 2.4
Name: fitinera
Version: 0.1.0
Summary: f-Itinera planning simulator library and examples
License-Expression: GPL-3.0-or-later
Requires-Dist: matplotlib>=3.10.3
Requires-Dist: numpy>=2.3.1
Requires-Dist: pandas>=2.3.3
Requires-Dist: seaborn>=0.13.2
Requires-Python: >=3.13
